sup/__init__.py
sup/ast.py
sup/cli.py
sup/debugger.py
sup/errors.py
sup/interpreter.py
sup/lsp_server.py
sup/lsp_utils.py
sup/mypy.ini
sup/optimizer.py
sup/parser.py
sup/sourcemap.py
sup/supfmt.py
sup/suplint.py
sup/transpiler.py
sup/typecheck.py
sup/vm.py
sup/wasm.py
sup/lexicon/english.json
sup/tools/__init__.py
sup/tools/bench_gates.py
sup/tools/benchmarks.py
sup/tools/coverage.py
sup/tools/mem_probe.py
sup/tools/profiler.py
sup/tools/registry_server.py
sup_lang-2.8.0.dist-info/METADATA
sup_lang-2.8.0.dist-info/WHEEL
sup_lang-2.8.0.dist-info/entry_points.txt
sup_lang-2.8.0.dist-info/RECORD
