Metadata-Version: 2.4
Name: sup-lang
Version: 2.8.0
Summary: Sup: an English-like programming language (MVP)
Project-URL: Homepage, https://github.com/Karthikprasadm/Sup
Project-URL: Repository, https://github.com/Karthikprasadm/Sup
Project-URL: Issues, https://github.com/Karthikprasadm/Sup/issues
Author: Sup Language Team
License: MIT
Classifier: License :: OSI Approved :: MIT License
Classifier: Operating System :: OS Independent
Classifier: Programming Language :: Python :: 3
Classifier: Programming Language :: Python :: 3 :: Only
Classifier: Topic :: Software Development :: Compilers
Requires-Python: >=3.9
